setup.py
bettadb/__init__.py
bettadb/client.py
bettadb/db.py
bettadb.egg-info/PKG-INFO
bettadb.egg-info/SOURCES.txt
bettadb.egg-info/dependency_links.txt
bettadb.egg-info/requires.txt
bettadb.egg-info/top_level.txt