Metadata-Version: 1.0
Name: bettadb
Version: 0.1.2
Summary: Simple-to-use embedded database, modelled on MongoDB
Home-page: https://github.com/ideaxod/bettaDB.git
Author: Jack Stephenson <jackatbancast>
Author-email: jack@bancast.net
License: UNKNOWN
Platform: UNKNOWN
